sis_extras-0.1.3.dist-info/METADATA
sis_extras-0.1.3.dist-info/WHEEL
sis_extras/__init__.py
sis_extras/connection.py
sis_extras/formatting.py
sis_extras-0.1.3.dist-info/RECORD
