Metadata-Version: 2.1
Name: sis-extras
Version: 0.1.3
Summary: Python package to make it easy to develop beautiful, performant streamlit-in-snowflake apps
Author-Email: Zachary Blackwood <zblackwo@gmail.com>
License: MIT
Classifier: License :: OSI Approved :: MIT License
Classifier: Programming Language :: Python :: 3.8
Project-URL: Source, https://github.com/blackary/sis-extras
Project-URL: Tracker, https://github.com/blackary/sis-extras/issues
Requires-Python: ==3.8.*
Requires-Dist: streamlit==1.31.1
Requires-Dist: snowflake-snowpark-python>=1.13.0
Requires-Dist: plotly>=5.20.0
